{
  "archivo_imagen": "clasificacion_20250909_181713_1.jpg",
  "timestamp_procesamiento": "2025-09-09T18:17:13.555443",
  "timestamp_captura": "20250909_181713",
  "tipo_analisis": "clasificacion",
  "version_metadatos": "1.0",
  "modelo": {
    "nombre": "CopleClasDef2C1V.onnx",
    "tipo": "clasificacion",
    "clases_disponibles": [
      "Aceptado",
      "Rechazado"
    ]
  },
  "imagen": {
    "resolucion": {
      "ancho": 640,
      "alto": 640,
      "canales": 3
    },
    "formato": "RGB",
    "tipo": "uint8"
  },
  "sistema": {
    "version": "1.0",
    "plataforma": "Linux",
    "framework": "ONNX Runtime"
  },
  "resultados": {
    "clasificacion": {
      "clase": "Rechazado",
      "confianza": 1.0,
      "tiempo_inferencia_ms": 48.74777793884277
    }
  },
  "tiempos": {
    "captura_ms": 91.40658378601074,
    "clasificacion_ms": 49.77917671203613,
    "total_ms": 141.18719100952148
  },
  "estadisticas": {
    "total_clasificaciones": 1,
    "confianza_promedio": 1.0,
    "confianza_maxima": 1.0,
    "confianza_minima": 1.0
  }
}